sphinx_peakrdl/__about__.py
sphinx_peakrdl/__init__.py
sphinx_peakrdl/build.py
sphinx_peakrdl/config.py
sphinx_peakrdl/design_state.py
sphinx_peakrdl/domain.py
sphinx_peakrdl/html.py
sphinx_peakrdl/utils.py
sphinx_peakrdl/directives/docnode.py
sphinx_peakrdl/directives/doctree.py
sphinx_peakrdl/directives/relative_to.py
sphinx_peakrdl/markdown/__init__.py
sphinx_peakrdl/markdown/docutils_renderer.py
sphinx_peakrdl/markdown/md_parsers.py
sphinx_peakrdl/markdown/render.py
sphinx_peakrdl/roles/__init__.py
sphinx_peakrdl/roles/xrefs.py
sphinx_peakrdl-0.2.0.dist-info/licenses/LICENSE
sphinx_peakrdl-0.2.0.dist-info/METADATA
sphinx_peakrdl-0.2.0.dist-info/WHEEL
sphinx_peakrdl-0.2.0.dist-info/top_level.txt
sphinx_peakrdl-0.2.0.dist-info/RECORD
